gammy/__init__.py
gammy/__version__.py
gammy/arraymapper.py
gammy/conftest.py
gammy/formulae.py
gammy/plot.py
gammy/utils.py
gammy/models/__init__.py
gammy/models/bayespy.py
gammy/models/numpy.py
gammy-0.5.6.dist-info/licenses/LICENSE.txt
gammy-0.5.6.dist-info/METADATA
gammy-0.5.6.dist-info/WHEEL
gammy-0.5.6.dist-info/top_level.txt
gammy-0.5.6.dist-info/RECORD
