Metadata-Version: 2.4
Name: gammy
Version: 0.5.6
Summary: Generalized additive models with a Bayesian twist
Home-page: https://malmgrek.github.io/gammy
Author: Stratos Staboulis <stratos@stratokraft.fi>
Maintainer: Stratos Staboulis <stratos@stratokraft.fi>
License: MIT
Keywords: bayesian,statistics,modeling,gaussian processes,splines
Classifier: Programming Language :: Python :: 3
Classifier: Development Status :: 3 - Alpha
Classifier: Intended Audience :: Science/Research
Classifier: Topic :: Scientific/Engineering :: Artificial Intelligence
Classifier: License :: OSI Approved :: MIT License
Classifier: Operating System :: OS Independent
License-File: LICENSE.txt
Requires-Dist: bayespy
Requires-Dist: h5py
Requires-Dist: numpy>=1.10.0
Requires-Dist: scipy>=0.13.0
Provides-Extra: test
Requires-Dist: pytest; extra == "test"
Provides-Extra: dev
Requires-Dist: build==1.3.0; extra == "dev"
Requires-Dist: matplotlib; extra == "dev"
Requires-Dist: pillow>=10.3.0; extra == "dev"
Requires-Dist: pip-tools==7.5.0; extra == "dev"
Requires-Dist: twine==6.1.0; extra == "dev"
Provides-Extra: doc
Requires-Dist: sphinx; extra == "doc"
Requires-Dist: numpydoc; extra == "doc"
Dynamic: license-file
